ai_programs/__init__.py
ai_programs/core.py
ai_programs_sam_gladson-0.1.2.dist-info/METADATA
ai_programs_sam_gladson-0.1.2.dist-info/WHEEL
ai_programs_sam_gladson-0.1.2.dist-info/top_level.txt
ai_programs_sam_gladson-0.1.2.dist-info/RECORD
