Metadata-Version: 2.4
Name: ai-programs-sam-gladson
Version: 0.1.2
Summary: AI and ML demo programs
License: MIT
Requires-Python: >=3.9
Requires-Dist: numpy
Requires-Dist: matplotlib
Requires-Dist: pandas
Requires-Dist: scikit-learn
Requires-Dist: tensorflow
Requires-Dist: SpeechRecognition
Requires-Dist: pyttsx3
